{
  "users": [
    {
      "id": "2e2e",
      "name": "Pat Cormier"
    },
    {
      "id": "6c7f",
      "name": "Mr. Angie Nicolas"
    },
    {
      "id": "6b7b",
      "name": "Lillian O'Conner"
    }
  ],
  "albums": [
    {
      "id": "ce24",
      "userId": null,
      "title": "Modern Granite Chair"
    },
    {
      "id": "30d1",
      "userId": null,
      "title": "Ergonomic Rubber Chicken"
    },
    {
      "id": "4fab",
      "userId": null,
      "title": "Practical Soft Fish"
    },
    {
      "id": "639b",
      "userId": null,
      "title": "Oriental Cotton Gloves"
    },
    {
      "id": "7c93",
      "userId": null,
      "title": "Modern Concrete Chair"
    },
    {
      "id": "31a1",
      "userId": null,
      "title": "Handcrafted Plastic Table"
    },
    {
      "id": "f5a8",
      "userId": null,
      "title": "Gorgeous Bronze Ball"
    },
    {
      "id": "02f0",
      "userId": null,
      "title": "Modern Concrete Pants"
    },
    {
      "id": "b417",
      "userId": null,
      "title": "Awesome Fresh Salad"
    },
    {
      "id": "0182",
      "userId": null,
      "title": "Generic Frozen Shoes"
    },
    {
      "id": "0dfc",
      "userId": null,
      "title": "Incredible Soft Keyboard"
    },
    {
      "id": "0ae3",
      "userId": null,
      "title": "Intelligent Plastic Shirt"
    },
    {
      "id": "3cb8",
      "userId": null,
      "title": "Tasty Fresh Bike"
    },
    {
      "id": "641a",
      "userId": null,
      "title": "Handcrafted Metal Tuna"
    },
    {
      "id": "8631",
      "userId": null,
      "title": "Handcrafted Wooden Mouse"
    },
    {
      "id": "62eb",
      "userId": null,
      "title": "Bespoke Granite Pizza"
    },
    {
      "id": "66e5",
      "userId": null,
      "title": "Fantastic Wooden Chicken"
    },
    {
      "id": "ab7f",
      "userId": null,
      "title": "Small Metal Shirt"
    },
    {
      "id": "db7f",
      "userId": null,
      "title": "Generic Bronze Fish"
    },
    {
      "id": "b5cf",
      "userId": null,
      "title": "Incredible Plastic Chicken"
    },
    {
      "id": "2fe7",
      "userId": null,
      "title": "Modern Metal Bike"
    },
    {
      "id": "a165",
      "userId": null,
      "title": "Small Plastic Salad"
    },
    {
      "id": "ee94",
      "userId": "2e2e",
      "title": "Recycled Plastic Towels"
    }
  ],
  "photos": [
    {
      "id": "fde8",
      "albumId": "ce24",
      "url": "https://loremflickr.com/150/150/abstract?lock=66546"
    },
    {
      "id": "081a",
      "albumId": "ce24",
      "url": "https://loremflickr.com/150/150/abstract?lock=58307"
    },
    {
      "id": "4067",
      "albumId": "ce24",
      "url": "https://loremflickr.com/150/150/abstract?lock=2830"
    },
    {
      "id": "9d22",
      "albumId": "ce24",
      "url": "https://loremflickr.com/150/150/abstract?lock=12226"
    },
    {
      "id": "188b",
      "albumId": "ce24",
      "url": "https://loremflickr.com/150/150/abstract?lock=7181"
    },
    {
      "id": "f510",
      "albumId": "ce24",
      "url": "https://loremflickr.com/150/150/abstract?lock=73562"
    },
    {
      "id": "589f",
      "albumId": "ce24",
      "url": "https://loremflickr.com/150/150/abstract?lock=11743"
    },
    {
      "id": "95d4",
      "albumId": "ce24",
      "url": "https://loremflickr.com/150/150/abstract?lock=39548"
    },
    {
      "id": "de7a",
      "albumId": "ce24",
      "url": "https://loremflickr.com/150/150/abstract?lock=50687"
    },
    {
      "id": "ed32",
      "albumId": "30d1",
      "url": "https://loremflickr.com/150/150/abstract?lock=49833"
    },
    {
      "id": "4578",
      "albumId": "30d1",
      "url": "https://loremflickr.com/150/150/abstract?lock=24234"
    },
    {
      "id": "b73c",
      "albumId": "30d1",
      "url": "https://loremflickr.com/150/150/abstract?lock=2218"
    },
    {
      "id": "b224",
      "albumId": "30d1",
      "url": "https://loremflickr.com/150/150/abstract?lock=15164"
    },
    {
      "id": "71c9",
      "albumId": "30d1",
      "url": "https://loremflickr.com/150/150/abstract?lock=33078"
    },
    {
      "id": "8440",
      "albumId": "4fab",
      "url": "https://loremflickr.com/150/150/abstract?lock=69777"
    },
    {
      "id": "1a10",
      "albumId": "4fab",
      "url": "https://loremflickr.com/150/150/abstract?lock=87847"
    },
    {
      "id": "48df",
      "albumId": "4fab",
      "url": "https://loremflickr.com/150/150/abstract?lock=921"
    },
    {
      "id": "0a4d",
      "albumId": "4fab",
      "url": "https://loremflickr.com/150/150/abstract?lock=54866"
    },
    {
      "id": "fa77",
      "albumId": "4fab",
      "url": "https://loremflickr.com/150/150/abstract?lock=28123"
    },
    {
      "id": "a3ff",
      "albumId": "4fab",
      "url": "https://loremflickr.com/150/150/abstract?lock=45579"
    },
    {
      "id": "37e6",
      "albumId": "4fab",
      "url": "https://loremflickr.com/150/150/abstract?lock=54231"
    },
    {
      "id": "2582",
      "albumId": "4fab",
      "url": "https://loremflickr.com/150/150/abstract?lock=86431"
    },
    {
      "id": "0a30",
      "albumId": "4fab",
      "url": "https://loremflickr.com/150/150/abstract?lock=6701"
    },
    {
      "id": "b962",
      "albumId": "ce24",
      "url": "https://loremflickr.com/150/150/abstract?lock=21758"
    },
    {
      "id": "ff84",
      "albumId": "30d1",
      "url": "https://loremflickr.com/150/150/abstract?lock=54499"
    },
    {
      "id": "8c0d",
      "albumId": "ee94",
      "url": "https://loremflickr.com/150/150/abstract?lock=63385"
    },
    {
      "id": "2c10",
      "albumId": "ee94",
      "url": "https://loremflickr.com/150/150/abstract?lock=22915"
    },
    {
      "id": "1785",
      "albumId": "ee94",
      "url": "https://loremflickr.com/150/150/abstract?lock=37653"
    },
    {
      "id": "197f",
      "albumId": "ee94",
      "url": "https://loremflickr.com/150/150/abstract?lock=71109"
    },
    {
      "id": "e0ba",
      "albumId": "ee94",
      "url": "https://loremflickr.com/150/150/abstract?lock=44400"
    },
    {
      "id": "e085",
      "albumId": "ee94",
      "url": "https://loremflickr.com/150/150/abstract?lock=46837"
    },
    {
      "id": "0e38",
      "albumId": "ee94",
      "url": "https://loremflickr.com/150/150/abstract?lock=60021"
    }
  ]
}